time_zone/__init__.py
time_zone/time_zone.py
time_zone_dict-1.6.1.dist-info/LICENSE
time_zone_dict-1.6.1.dist-info/METADATA
time_zone_dict-1.6.1.dist-info/WHEEL
time_zone_dict-1.6.1.dist-info/top_level.txt
time_zone_dict-1.6.1.dist-info/RECORD
